trustllm/__init__.py
trustllm/config.py
trustllm/dataset_download.py
trustllm/generation/__init__.py
trustllm/generation/generation.py
trustllm/prompt/model_info.json
trustllm/prompt/task_prompt.json
trustllm/task/__init__.py
trustllm/task/ethics.py
trustllm/task/fairness.py
trustllm/task/pipeline.py
trustllm/task/privacy.py
trustllm/task/robustness.py
trustllm/task/safety.py
trustllm/task/truthfulness.py
trustllm/utils/__init__.py
trustllm/utils/embedder.py
trustllm/utils/file_process.py
trustllm/utils/generation_utils.py
trustllm/utils/gpt_auto_eval.py
trustllm/utils/longformer.py
trustllm/utils/metrics.py
trustllm/utils/perspective.py
trustllm-0.3.0.dist-info/METADATA
trustllm-0.3.0.dist-info/WHEEL
trustllm-0.3.0.dist-info/top_level.txt
trustllm-0.3.0.dist-info/RECORD
